<?xml version="1.0" encoding="UTF-8" standalone="no"?>
<tabLinespecsUnits>
<RowLinespecUnit description="Строка спецификации - ед.изм № 1 4" id="1" id2="4"/>
<RowLinespecUnit description="Строка спецификации - ед.изм № 2 4" id="2" id2="4"/>
<RowLinespecUnit description="Строка спецификации - ед.изм № 3 5" id="3" id2="5"/>
<RowLinespecUnit description="Строка спецификации - ед.изм № 4 1" id="4" id2="1"/>
<RowLinespecUnit description="Строка спецификации - ед.изм № 5 4" id="5" id2="4"/>
<RowLinespecUnit description="Строка спецификации - ед.изм № 6 2" id="6" id2="2"/>
<RowLinespecUnit description="Строка спецификации - ед.изм № 7 2" id="7" id2="2"/>
<RowLinespecUnit description="   " id="13" id2="2"/>
<RowLinespecUnit description="   " id="19" id2="2"/>
<RowLinespecUnit description="   " id="10" id2="2"/>
<RowLinespecUnit description="   " id="18" id2="2"/>
<RowLinespecUnit description="   " id="8" id2="2"/>
<RowLinespecUnit description="   " id="17" id2="2"/>
<RowLinespecUnit description="   " id="9" id2="2"/>
<RowLinespecUnit description="   " id="16" id2="2"/>
<RowLinespecUnit description="   " id="11" id2="2"/>
<RowLinespecUnit description="   " id="15" id2="2"/>
<RowLinespecUnit description="   " id="14" id2="2"/>
<RowLinespecUnit description="   " id="12" id2="2"/>
<RowLinespecUnit description="   " id="20" id2="6"/>
<RowLinespecUnit description="   " id="21" id2="7"/>
<RowLinespecUnit description="   " id="22" id2="8"/>
<RowLinespecUnit description="   " id="23" id2="9"/>
<RowLinespecUnit description="   " id="24" id2="10"/>
<RowLinespecUnit description="   " id="25" id2="11"/>
<RowLinespecUnit description="   " id="26" id2="12"/>
<RowLinespecUnit description="   " id="27" id2="13"/>
<RowLinespecUnit description="   " id="28" id2="14"/>
<RowLinespecUnit description="   " id="29" id2="15"/>
<RowLinespecUnit description="   " id="30" id2="16"/>
<RowLinespecUnit description="   " id="31" id2="17"/>
<RowLinespecUnit description="   " id="32" id2="18"/>
<RowLinespecUnit description="   " id="33" id2="19"/>
<RowLinespecUnit description="   " id="34" id2="20"/>
<RowLinespecUnit description="   " id="35" id2="21"/>
<RowLinespecUnit description="   " id="36" id2="22"/>
<RowLinespecUnit description="   " id="37" id2="23"/>
<RowLinespecUnit description="   " id="38" id2="24"/>
<RowLinespecUnit description="   " id="39" id2="25"/>
<RowLinespecUnit description="   " id="40" id2="26"/>
<RowLinespecUnit description="   " id="41" id2="27"/>
<RowLinespecUnit description="   " id="42" id2="28"/>
<RowLinespecUnit description="   " id="43" id2="29"/>
<RowLinespecUnit description="   " id="44" id2="30"/>
<RowLinespecUnit description="   " id="45" id2="31"/>
<RowLinespecUnit description="   " id="46" id2="32"/>
<RowLinespecUnit description="   " id="47" id2="33"/>
<RowLinespecUnit description="   " id="48" id2="34"/>
<RowLinespecUnit description="   " id="49" id2="35"/>
<RowLinespecUnit description="   " id="50" id2="36"/>
<RowLinespecUnit description="   " id="51" id2="37"/>
<RowLinespecUnit description="   " id="52" id2="38"/>
<RowLinespecUnit description="   " id="53" id2="39"/>
<RowLinespecUnit description="   " id="54" id2="40"/>
<RowLinespecUnit description="   " id="55" id2="41"/>
<RowLinespecUnit description="   " id="56" id2="42"/>
<RowLinespecUnit description="   " id="57" id2="43"/>
<RowLinespecUnit description="   " id="58" id2="44"/>
<RowLinespecUnit description="   " id="59" id2="45"/>
<RowLinespecUnit description="   " id="60" id2="46"/>
<RowLinespecUnit description="   " id="61" id2="47"/>
<RowLinespecUnit description="   " id="62" id2="48"/>
<RowLinespecUnit description="   " id="63" id2="49"/>
<RowLinespecUnit description="   " id="64" id2="50"/>
<RowLinespecUnit description="   " id="65" id2="51"/>
<RowLinespecUnit description="   " id="66" id2="52"/>
<RowLinespecUnit description="   " id="67" id2="53"/>
</tabLinespecsUnits>
