<?xml version="1.0" encoding="UTF-8" standalone="no"?>
<tabRoutes>
<RowRoute description="Описание теx.маршрута №1" id="1" name="ТехМаршрут №1"/>
<RowRoute description="Описание теx.маршрута №4" id="4" name="ТехМаршрут №4"/>
<RowRoute description="Описание теx.маршрута №5" id="5" name="ТехМаршрут №5"/>
<RowRoute description="Описание теx.маршрута №6" id="6" name="ТехМаршрут №6"/>
<RowRoute description="Описание теx.маршрута №7" id="7" name="ТехМаршрут №7"/>
<RowRoute description="Описание теx.маршрута №8" id="8" name="ТехМаршрут №8"/>
<RowRoute description="Описание теx.маршрута №9" id="9" name="ТехМаршрут №9"/>
<RowRoute description="Описание теx.маршрута №10" id="10" name="ТехМаршрут №10"/>
<RowRoute description="Описание теx.маршрута №11" id="11" name="ТехМаршрут №11"/>
<RowRoute description="Описание теx.маршрута №13" id="13" name="ТехМаршрут №13"/>
<RowRoute description="Описание теx.маршрута №14" id="14" name="ТехМаршрут №14"/>
<RowRoute description="Описание теx.маршрута №15" id="15" name="ТехМаршрут №15"/>
<RowRoute description="Описание теx.маршрута №16" id="16" name="ТехМаршрут №16"/>
<RowRoute description="Описание теx.маршрута №17" id="17" name="ТехМаршрут №17"/>
<RowRoute description="Описание теx.маршрута №18" id="18" name="ТехМаршрут №18"/>
<RowRoute description="Описание теx.маршрута №19" id="19" name="ТехМаршрут №19"/>
<RowRoute description="Описание для    RowRoute" id="2" name="RowRoute№2"/>
<RowRoute description="Описание для    RowRoute" id="20" name="RowRoute№20"/>
<RowRoute description="Описание для    RowRoute" id="21" name="RowRoute№21"/>
<RowRoute description="Описание для    RowRoute" id="22" name="RowRoute№22"/>
<RowRoute description="Описание для    RowRoute" id="23" name="RowRoute№23"/>
<RowRoute description="Описание для    RowRoute" id="24" name="RowRoute№24"/>
<RowRoute description="Описание для    RowRoute" id="25" name="RowRoute№25"/>
<RowRoute description="Описание для    RowRoute" id="26" name="RowRoute№26"/>
<RowRoute description="Описание для    RowRoute" id="27" name="RowRoute№27"/>
<RowRoute description="Описание для    RowRoute" id="28" name="RowRoute№28"/>
<RowRoute description="Описание для    RowRoute" id="29" name="RowRoute№29"/>
<RowRoute description="Описание для    RowRoute" id="30" name="RowRoute№30"/>
<RowRoute description="Описание для    RowRoute" id="31" name="RowRoute№31"/>
<RowRoute description="Описание для    RowRoute" id="32" name="RowRoute№32"/>
<RowRoute description="Описание для    RowRoute" id="33" name="RowRoute№33"/>
<RowRoute description="Описание для    RowRoute" id="34" name="RowRoute№34"/>
<RowRoute description="Описание для    RowRoute" id="35" name="RowRoute№35"/>
<RowRoute description="Описание для    RowRoute" id="36" name="RowRoute№36"/>
<RowRoute description="Описание для    RowRoute" id="37" name="RowRoute№37"/>
<RowRoute description="Описание для    RowRoute" id="38" name="RowRoute№38"/>
<RowRoute description="Описание для    RowRoute" id="39" name="RowRoute№39"/>
<RowRoute description="Описание для    RowRoute" id="40" name="RowRoute№40"/>
<RowRoute description="Описание для    RowRoute" id="41" name="RowRoute№41"/>
<RowRoute description="Описание для    RowRoute" id="42" name="RowRoute№42"/>
<RowRoute description="Описание для    Route" id="43" name="Route№43"/>
<RowRoute description="Описание для    Route" id="44" name="Route№44"/>
<RowRoute description="Описание для    RowRoute" id="45" name="RowRoute№45"/>
<RowRoute description="Описание для    Route" id="46" name="Route№46"/>
<RowRoute description="Описание для    Route" id="47" name="Route№47"/>
</tabRoutes>
